directory_tree/__init__.py
directory_tree/__main__.py
directory_tree/tree_calculator.py
directory_tree/tree_cli.py
directory_tree/tree_driver.py
directory_tree/version.py
directory_tree-1.0.0.dist-info/LICENSE
directory_tree-1.0.0.dist-info/METADATA
directory_tree-1.0.0.dist-info/WHEEL
directory_tree-1.0.0.dist-info/entry_points.txt
directory_tree-1.0.0.dist-info/top_level.txt
directory_tree-1.0.0.dist-info/RECORD
