Metadata-Version: 2.1
Name: directory_tree
Version: 1.0.0
Summary: Utility Package that Displays out the Tree Structure of a Particular Directory.
Home-page: https://github.com/rahulbordoloi/Directory-Tree/
Author: Rahul Bordoloi
Author-email: rahulbordoloi24@gmail.com
Classifier: Programming Language :: Python :: 3.5
Classifier: Programming Language :: Python :: 3.6
Classifier: Programming Language :: Python :: 3.7
Classifier: Programming Language :: Python :: 3.8
Classifier: Programming Language :: Python :: 3.9
Classifier: Programming Language :: Python :: 3.10
Classifier: Programming Language :: Python :: 3.11
Classifier: Programming Language :: Python :: 3.12
Classifier: Operating System :: OS Independent
Classifier: License :: OSI Approved :: GNU General Public License v3 (GPLv3)
Classifier: Topic :: Utilities
Classifier: Natural Language :: English
Classifier: Development Status :: 5 - Production/Stable
Classifier: Intended Audience :: Customer Service
Classifier: Intended Audience :: Developers
Classifier: Intended Audience :: End Users/Desktop
License-File: LICENSE
Provides-Extra: dev
Requires-Dist: pytest>=3.7; extra == "dev"
